LICENSE
MANIFEST.in
README.md
setup.cfg
setup.py
tap_invoiced/__init__.py
tap_invoiced/discover.py
tap_invoiced/sync.py
tap_invoiced.egg-info/PKG-INFO
tap_invoiced.egg-info/SOURCES.txt
tap_invoiced.egg-info/dependency_links.txt
tap_invoiced.egg-info/entry_points.txt
tap_invoiced.egg-info/requires.txt
tap_invoiced.egg-info/top_level.txt
tap_invoiced/schemas/credit_notes.json
tap_invoiced/schemas/customers.json
tap_invoiced/schemas/estimates.json
tap_invoiced/schemas/invoices.json
tap_invoiced/schemas/plans.json
tap_invoiced/schemas/subscriptions.json
tap_invoiced/schemas/transactions.json